{
  "updated": "2026-02-26T23:51:21.146Z",
  "channelId": "UCQZv6ak1WpuZLoqz0FT1aqg",
  "items": [
    {
      "id": "rV8rUEqMSGg",
      "title": "Dragons vs Soldiers B HOBBY 26.02.2026",
      "thumbnail": "https://i.ytimg.com/vi/rV8rUEqMSGg/mqdefault.jpg",
      "isLive": false,
      "publishedAt": "2026-02-26T21:03:24Z"
    },
    {
      "id": "Zttggf_EFJY",
      "title": "Fotr vs Phantoms HOBBY 26.02.2026",
      "thumbnail": "https://i.ytimg.com/vi/Zttggf_EFJY/mqdefault.jpg",
      "isLive": false,
      "publishedAt": "2026-02-26T20:27:45Z"
    },
    {
      "id": "9y5d6XEvtn8",
      "title": "Vikings vs Traverzáci HOBBY 26.02.2026",
      "thumbnail": "https://i.ytimg.com/vi/9y5d6XEvtn8/mqdefault.jpg",
      "isLive": false,
      "publishedAt": "2026-02-26T19:44:34Z"
    },
    {
      "id": "TH1qv9vTN9o",
      "title": "Stars vs Alligators KLASIK 26.02.2026",
      "thumbnail": "https://i.ytimg.com/vi/TH1qv9vTN9o/mqdefault.jpg",
      "isLive": false,
      "publishedAt": "2026-02-26T18:57:51Z"
    },
    {
      "id": "ETwHbV0LI-g",
      "title": "55 Girls Hockey vs Icerink W Prague 26.02.2026",
      "thumbnail": "https://i.ytimg.com/vi/ETwHbV0LI-g/mqdefault.jpg",
      "isLive": false,
      "publishedAt": "2026-02-26T11:14:39Z"
    },
    {
      "id": "EMzn4chNHtE",
      "title": "Žraloci vs Paladins HOBBY 25.02.2026",
      "thumbnail": "https://i.ytimg.com/vi/EMzn4chNHtE/mqdefault.jpg",
      "isLive": false,
      "publishedAt": "2026-02-26T09:57:02Z"
    },
    {
      "id": "_fOiKIvYv5g",
      "title": "Ducks C vs MyQ HOBBY 25.02.2026",
      "thumbnail": "https://i.ytimg.com/vi/_fOiKIvYv5g/mqdefault.jpg",
      "isLive": false,
      "publishedAt": "2026-02-26T08:36:47Z"
    }
  ]
}