{
  "updated": "2026-03-08T16:21:21.793Z",
  "channelId": "UCQZv6ak1WpuZLoqz0FT1aqg",
  "items": [
    {
      "id": "2b3fCidFKNg",
      "title": "Cheza vs Rats SPORT 8.3.2026",
      "thumbnail": "https://i.ytimg.com/vi/2b3fCidFKNg/mqdefault_live.jpg",
      "isLive": true,
      "publishedAt": "2026-03-08T16:15:30Z"
    },
    {
      "id": "ab4q_eRle7E",
      "title": "SLZ vs CHI, KLASIK, 08.03.2026",
      "thumbnail": "https://i.ytimg.com/vi/ab4q_eRle7E/mqdefault_live.jpg",
      "isLive": true,
      "publishedAt": "2026-03-08T16:07:54Z"
    },
    {
      "id": "cqZm0jGvbNA",
      "title": "Vikings vs Ducks C Hobby 08.03.2026",
      "thumbnail": "https://i.ytimg.com/vi/cqZm0jGvbNA/mqdefault.jpg",
      "isLive": false,
      "publishedAt": "2026-03-08T14:53:45Z"
    },
    {
      "id": "IllriSydE_I",
      "title": "Vikings vs Ducks C Hobby 08.03.2026",
      "thumbnail": "https://i.ytimg.com/vi/IllriSydE_I/mqdefault.jpg",
      "isLive": false,
      "publishedAt": "2026-03-08T14:50:31Z"
    },
    {
      "id": "7F4szoS_vOc",
      "title": "Soldiers B vs Papoušci HOBBY 8.3.2026",
      "thumbnail": "https://i.ytimg.com/vi/7F4szoS_vOc/mqdefault.jpg",
      "isLive": false,
      "publishedAt": "2026-03-08T14:43:29Z"
    },
    {
      "id": "xn4Z9BGFFUk",
      "title": "Fanklub vs H.O.V.N.A. Sport 08.03.2026",
      "thumbnail": "https://i.ytimg.com/vi/xn4Z9BGFFUk/mqdefault.jpg",
      "isLive": false,
      "publishedAt": "2026-03-08T13:06:07Z"
    },
    {
      "id": "XYapzUi7g0A",
      "title": "Reindeers vs MyQ HOBBY 07.03.2026",
      "thumbnail": "https://i.ytimg.com/vi/XYapzUi7g0A/mqdefault.jpg",
      "isLive": false,
      "publishedAt": "2026-03-08T02:05:16Z"
    }
  ]
}